wlmclear/__init__.py
wlmclear-1.0.0.dist-info/METADATA
wlmclear-1.0.0.dist-info/WHEEL
wlmclear-1.0.0.dist-info/RECORD
